README.rst
setup.py
prettystring/__init__.py
prettystring/prettystring.py
prettystring/util.py
prettystring.egg-info/PKG-INFO
prettystring.egg-info/SOURCES.txt
prettystring.egg-info/dependency_links.txt
prettystring.egg-info/requires.txt
prettystring.egg-info/top_level.txt