Metadata-Version: 1.1
Name: prettystring
Version: 0.1.1
Summary: Build ANSI color encoded strings with ease.
Home-page: https://github.com/robolivable/prettystring
Author: Robert Oliveira
Author-email: oliveira.rlde@gmail.com
License: MIT
Keywords: color colorful pretty string strings
Platform: UNKNOWN
Classifier: Development Status :: 2 - Pre-Alpha
Classifier: Environment :: Console
Classifier: License :: OSI Approved :: MIT License
Classifier: Programming Language :: Python :: 2.7
Classifier: Topic :: Software Development
Classifier: Topic :: Software Development :: Libraries :: Python Modules
Classifier: Topic :: Software Development :: User Interfaces
Classifier: Topic :: Terminals
Classifier: Topic :: Text Processing :: General
Classifier: Topic :: Utilities
